hs_dbus_signature/__init__.py
hs_dbus_signature/_signature.py
hs_dbus_signature/_version.py
hs_dbus_signature-0.7.dist-info/LICENSE.txt
hs_dbus_signature-0.7.dist-info/METADATA
hs_dbus_signature-0.7.dist-info/WHEEL
hs_dbus_signature-0.7.dist-info/top_level.txt
hs_dbus_signature-0.7.dist-info/RECORD
