Metadata-Version: 2.1
Name: hs-dbus-signature
Version: 0.7
Summary: dbus signature hypothesis strategy generator
Home-page: https://github.com/stratis-storage/hs-dbus-signature
Author: Anne Mulhern
Author-email: amulhern@redhat.com
License: MPL v2
Platform: Linux
Classifier: Development Status :: 4 - Beta
Classifier: Framework :: Hypothesis
Classifier: Intended Audience :: Developers
Classifier: License :: OSI Approved :: Mozilla Public License 2.0 (MPL 2.0)
Classifier: Operating System :: POSIX :: Linux
Classifier: Programming Language :: Python
Classifier: Programming Language :: Python :: 3
Classifier: Programming Language :: Python :: Implementation :: CPython
Classifier: Programming Language :: Python :: Implementation :: PyPy
Classifier: Topic :: Software Development :: Libraries
Classifier: Topic :: Software Development :: Libraries :: Python Modules
Classifier: Topic :: Software Development :: Testing
Requires-Dist: hypothesis
